audiodriller/__init__.py
audiodriller/driller.py
audiodriller-0.1.0.dist-info/WHEEL
audiodriller-0.1.0.dist-info/METADATA
audiodriller-0.1.0.dist-info/RECORD
