Metadata-Version: 2.1
Name: audiodriller
Version: 0.1.0
Summary: A tool for structured, efficient ear training using real recorded audio.
Author: Vincent Nys
Author-email: vincentnys@gmail.com
Requires-Python: >=3.10,<4.0
Classifier: Programming Language :: Python :: 3
Classifier: Programming Language :: Python :: 3.10
Requires-Dist: PyInputPlus (>=0.2.12,<0.3.0)
Requires-Dist: click (>=8.1.3,<9.0.0)
Requires-Dist: dataclasses-json (>=0.5.7,<0.6.0)
Requires-Dist: pydub (>=0.25.1,<0.26.0)
Requires-Dist: rich (>=12.5.1,<13.0.0)
Requires-Dist: simpleaudio (>=1.0.4,<2.0.0)
